awsuse/__init__.py
awsuse/cli.py
awsuse-0.1.2.dist-info/LICENSE
awsuse-0.1.2.dist-info/WHEEL
awsuse-0.1.2.dist-info/entry_points.txt
awsuse-0.1.2.dist-info/METADATA
awsuse-0.1.2.dist-info/RECORD
