Metadata-Version: 2.1
Name: awsuse
Version: 0.1.2
Summary: CLI to switch the aws cli default profile quickly
Home-page: https://github.com/aflopes/awsuse
Author: Andre Lopes
Author-email: afsalopes@gmail.com
Requires-Python: >=3.10,<4.0
Classifier: Programming Language :: Python :: 3
Classifier: Programming Language :: Python :: 3.10
Classifier: Programming Language :: Python :: 3.11
Requires-Dist: boto3 (>=1.26.56,<2.0.0)
Requires-Dist: click (>=8.1.3,<9.0.0)
Project-URL: Repository, https://github.com/aflopes/awsuse
